browser_use_recorder/README.md
browser_use_recorder/__init__.py
browser_use_recorder/logging_config.py
browser_use_recorder/utils.py
browser_use_recorder/agent/gif.py
browser_use_recorder/agent/prompts.py
browser_use_recorder/agent/service.py
browser_use_recorder/agent/system_prompt.md
browser_use_recorder/agent/tests.py
browser_use_recorder/agent/views.py
browser_use_recorder/agent/message_manager/service.py
browser_use_recorder/agent/message_manager/tests.py
browser_use_recorder/agent/message_manager/utils.py
browser_use_recorder/agent/message_manager/views.py
browser_use_recorder/browser/browser.py
browser_use_recorder/browser/context.py
browser_use_recorder/browser/views.py
browser_use_recorder/browser/tests/screenshot_test.py
browser_use_recorder/browser/tests/test_clicks.py
browser_use_recorder/controller/service.py
browser_use_recorder/controller/views.py
browser_use_recorder/controller/registry/service.py
browser_use_recorder/controller/registry/views.py
browser_use_recorder/dom/__init__.py
browser_use_recorder/dom/buildDomTree.js
browser_use_recorder/dom/service.py
browser_use_recorder/dom/views.py
browser_use_recorder/dom/history_tree_processor/service.py
browser_use_recorder/dom/history_tree_processor/view.py
browser_use_recorder/dom/tests/debug_page_structure.py
browser_use_recorder/dom/tests/extraction_test.py
browser_use_recorder/dom/tests/process_dom_test.py
browser_use_recorder/telemetry/service.py
browser_use_recorder/telemetry/views.py
browser_use_recorder-0.1.41.dist-info/METADATA
browser_use_recorder-0.1.41.dist-info/WHEEL
browser_use_recorder-0.1.41.dist-info/licenses/LICENSE
browser_use_recorder-0.1.41.dist-info/RECORD
