Metadata-Version: 2.4
Name: browser-use-recorder
Version: 0.1.41
Summary: Make websites accessible for AI agents
Project-URL: Repository, https://github.com/browser-use/browser-use-recorder
Author: Gregor Zunic
License-File: LICENSE
Classifier: License :: OSI Approved :: MIT License
Classifier: Operating System :: OS Independent
Classifier: Programming Language :: Python :: 3
Requires-Python: <4.0,>=3.11
Requires-Dist: httpx>=0.27.2
Requires-Dist: langchain-anthropic==0.3.3
Requires-Dist: langchain-core==0.3.35
Requires-Dist: langchain-ollama==0.2.2
Requires-Dist: langchain-openai==0.3.1
Requires-Dist: markdownify==1.1.0
Requires-Dist: playwright>=1.49.0
Requires-Dist: posthog>=3.7.0
Requires-Dist: pydantic>=2.10.4
Requires-Dist: python-dotenv>=1.0.1
Requires-Dist: requests>=2.32.3
Requires-Dist: setuptools>=75.8.0
Provides-Extra: dev
Requires-Dist: build>=1.2.2; extra == 'dev'
Requires-Dist: fastapi>=0.115.8; extra == 'dev'
Requires-Dist: hatch>=1.13.0; extra == 'dev'
Requires-Dist: inngest>=0.4.19; extra == 'dev'
Requires-Dist: langchain-aws>=0.2.11; extra == 'dev'
Requires-Dist: langchain-fireworks>=0.2.6; extra == 'dev'
Requires-Dist: langchain-google-genai==2.0.8; extra == 'dev'
Requires-Dist: langchain>=0.3.18; extra == 'dev'
Requires-Dist: pytest-asyncio>=0.24.0; extra == 'dev'
Requires-Dist: pytest>=8.3.3; extra == 'dev'
Requires-Dist: tokencost>=0.1.16; extra == 'dev'
Requires-Dist: uvicorn>=0.34.0; extra == 'dev'
